file_resubmit/__init__.py
file_resubmit/admin.py
file_resubmit/cache.py
file_resubmit/widgets.py
bw_file_resubmit-0.6.0rc2.dist-info/LICENSE
bw_file_resubmit-0.6.0rc2.dist-info/METADATA
bw_file_resubmit-0.6.0rc2.dist-info/WHEEL
bw_file_resubmit-0.6.0rc2.dist-info/top_level.txt
bw_file_resubmit-0.6.0rc2.dist-info/RECORD
