Metadata-Version: 2.1
Name: bw-file-resubmit
Version: 0.6.0rc2
Summary: Preserve files in Django forms during form validation errors. Drop-in replacement for django-file-resubmit
Author-email: Ilya Shalyapin <ishalyapin@gmail.com>, Hugh Rundle <hugh@hughrundle.net>
Maintainer-email: Hugh Rundle <hugh@hughrundle.net>
License: MIT License
Project-URL: Homepage, https://github.com/bookwyrm-social/bw-file-resubmit
Project-URL: Bug Tracker, https://github.com/bookwyrm-social/bw-file-resubmit/issues
Keywords: django,form,filefield,imagefield,resubmit,cache
Classifier: Environment :: Web Environment
Classifier: Framework :: Django
Classifier: Intended Audience :: Developers
Classifier: Programming Language :: Python :: 3
Classifier: License :: OSI Approved :: MIT License
Classifier: Operating System :: OS Independent
Requires-Python: >=3.7
License-File: LICENSE
